notion_writer/__init__.py
notion_writer/notion_block.py
notion_writer/notion_connector.py
notion_writer/notion_page.py
notion_writer-0.0.5.dist-info/LICENSE
notion_writer-0.0.5.dist-info/METADATA
notion_writer-0.0.5.dist-info/WHEEL
notion_writer-0.0.5.dist-info/top_level.txt
notion_writer-0.0.5.dist-info/RECORD
